indexed/__init__.py
indexed-1.3.0.dist-info/LICENSE
indexed-1.3.0.dist-info/METADATA
indexed-1.3.0.dist-info/WHEEL
indexed-1.3.0.dist-info/top_level.txt
indexed-1.3.0.dist-info/RECORD
