Metadata-Version: 2.1
Name: indexed
Version: 1.3.0
Summary: A dictionary that is indexed by insertion order.
Home-page: http://github.com/niklasf/indexed.py
Author: Niklas Fiekas
Author-email: niklas.fiekas@backscattering.de
License: PSFL
Classifier: Development Status :: 5 - Production/Stable
Classifier: Intended Audience :: Developers
Classifier: License :: OSI Approved :: Python Software Foundation License
Classifier: Operating System :: OS Independent
Classifier: Programming Language :: Python
Classifier: Programming Language :: Python :: 3
Classifier: Topic :: Software Development :: Libraries :: Python Modules
License-File: LICENSE
